llama_index/readers/readwise/__init__.py
llama_index/readers/readwise/base.py
llama_index_readers_readwise-0.4.1.dist-info/METADATA
llama_index_readers_readwise-0.4.1.dist-info/WHEEL
llama_index_readers_readwise-0.4.1.dist-info/licenses/LICENSE
llama_index_readers_readwise-0.4.1.dist-info/RECORD
