Metadata-Version: 2.4
Name: llama-index-readers-readwise
Version: 0.4.1
Summary: llama-index readers readwise integration
Author-email: Your Name <you@example.com>
Maintainer: alexbowe
License-Expression: MIT
License-File: LICENSE
Keywords: highlights,pkm,reading,readwise
Requires-Python: <4.0,>=3.9
Requires-Dist: llama-index-core<0.15,>=0.13.0
